psql_yy/__about__.py
psql_yy/__init__.py
psql_yy/psql_db.py
psql_yy/lib/SERVER_STATUS.py
psql_yy/lib/__init__.py
psql_yy/lib/_compat.py
psql_yy/lib/charset.py
psql_yy/lib/converters.py
psql_yy/lib/settings.py
psql_yy/lib/tool.py
psql_yy/lib/constants/FIELD_TYPE.py
psql_yy/lib/constants/FLAG.py
psql_yy/lib/constants/__init__.py
psql_yy-0.1.6.dist-info/LICENSE
psql_yy-0.1.6.dist-info/METADATA
psql_yy-0.1.6.dist-info/WHEEL
psql_yy-0.1.6.dist-info/top_level.txt
psql_yy-0.1.6.dist-info/RECORD
