Metadata-Version: 2.1
Name: psql-yy
Version: 0.1.6
Summary: A tool which is used to connect postgresql, designed by yy
Home-page: https://github.com/guaidashu/psql_yy
Author: guaidashu
Author-email: song42960@gmail.com
License: MIT
Platform: UNKNOWN
Classifier: Topic :: Internet :: WWW/HTTP :: Dynamic Content
Classifier: Programming Language :: Python :: 3
Classifier: Programming Language :: Python :: 3.5
Classifier: Programming Language :: Python :: 3.5
Classifier: Programming Language :: Python :: 3.6
Classifier: Programming Language :: Python :: 3.7
Requires-Dist: psycopg2 (<=2.8.3)
